LICENSE
MANIFEST.in
README.md
setup.cfg
setup.py
strictfire/__init__.py
strictfire/__main__.py
strictfire/completion.py
strictfire/completion_test.py
strictfire/core.py
strictfire/core_test.py
strictfire/custom_descriptions.py
strictfire/custom_descriptions_test.py
strictfire/decorators.py
strictfire/decorators_test.py
strictfire/docstrings.py
strictfire/docstrings_fuzz_test.py
strictfire/docstrings_test.py
strictfire/fire_import_test.py
strictfire/fire_test.py
strictfire/formatting.py
strictfire/formatting_test.py
strictfire/formatting_windows.py
strictfire/helptext.py
strictfire/helptext_test.py
strictfire/inspectutils.py
strictfire/inspectutils_test.py
strictfire/interact.py
strictfire/interact_test.py
strictfire/main_test.py
strictfire/parser.py
strictfire/parser_fuzz_test.py
strictfire/parser_test.py
strictfire/test_components.py
strictfire/test_components_bin.py
strictfire/test_components_py3.py
strictfire/test_components_test.py
strictfire/testutils.py
strictfire/testutils_test.py
strictfire/trace.py
strictfire/trace_test.py
strictfire/value_types.py
strictfire.egg-info/PKG-INFO
strictfire.egg-info/SOURCES.txt
strictfire.egg-info/dependency_links.txt
strictfire.egg-info/requires.txt
strictfire.egg-info/top_level.txt
strictfire/console/__init__.py
strictfire/console/console_attr.py
strictfire/console/console_attr_os.py
strictfire/console/console_io.py
strictfire/console/console_pager.py
strictfire/console/encoding.py
strictfire/console/files.py
strictfire/console/platforms.py
strictfire/console/text.py